{"cameraMode":{"drawMode":0,"name":"Shaded","section":"Shading Mode"},"sceneLighting":false,"audioPlay":false,"sceneViewState":{"m_AlwaysRefresh":false,"showFog":true,"showSkybox":false,"showFlares":true,"showImageEffects":true,"showParticleSystems":true,"showVisualEffectGraphs":true,"m_FxEnabled":true},"in2DMode":false,"pivot":{"x":347.58984375,"y":23.405269622802736,"z":642.6721801757813},"rotation":{"x":0.0006635670433752239,"y":-0.8974282741546631,"z":0.0013449479592964054,"w":0.4411686658859253},"size":18.706249237060548,"orthographic":false}